MANIFEST.in
README
distribute_setup.py
setup.cfg
setup.py
PyModelFit.egg-info/PKG-INFO
PyModelFit.egg-info/SOURCES.txt
PyModelFit.egg-info/dependency_links.txt
PyModelFit.egg-info/requires.txt
PyModelFit.egg-info/top_level.txt
docs/FitGuiExample1.png
docs/Makefile
docs/builtins.rst
docs/conf.py
docs/core.rst
docs/gui.rst
docs/index.rst
docs/make.bat
docs/over.rst
docs/start.rst
docs/_templates/autosummary/class.rst
docs/build/plot_directive/inline/abaf3d5d0b.hires.png
docs/build/plot_directive/inline/abaf3d5d0b.pdf
docs/build/plot_directive/inline/abaf3d5d0b.png
docs/builtins/pymodelfit.builtins.AlphaBetaGammaModel.rst
docs/builtins/pymodelfit.builtins.ConstantModel.rst
docs/builtins/pymodelfit.builtins.DoubleGaussianModel.rst
docs/builtins/pymodelfit.builtins.DoubleOpposedGaussianModel.rst
docs/builtins/pymodelfit.builtins.ExponentialModel.rst
docs/builtins/pymodelfit.builtins.FourierModel.rst
docs/builtins/pymodelfit.builtins.Gaussian2DModel.rst
docs/builtins/pymodelfit.builtins.GaussianModel.rst
docs/builtins/pymodelfit.builtins.InterpolatedSplineModel.rst
docs/builtins/pymodelfit.builtins.Linear2DModel.rst
docs/builtins/pymodelfit.builtins.LinearInterpolatedModel.rst
docs/builtins/pymodelfit.builtins.LinearModel.rst
docs/builtins/pymodelfit.builtins.LognormalModel.rst
docs/builtins/pymodelfit.builtins.LorentzianModel.rst
docs/builtins/pymodelfit.builtins.MaxwellBoltzmannModel.rst
docs/builtins/pymodelfit.builtins.MaxwellBoltzmannSpeedModel.rst
docs/builtins/pymodelfit.builtins.NearestInterpolatedModel.rst
docs/builtins/pymodelfit.builtins.Plane.rst
docs/builtins/pymodelfit.builtins.PolynomialModel.rst
docs/builtins/pymodelfit.builtins.PowerLawModel.rst
docs/builtins/pymodelfit.builtins.QuadraticModel.rst
docs/builtins/pymodelfit.builtins.SinModel.rst
docs/builtins/pymodelfit.builtins.SmoothSplineModel.rst
docs/builtins/pymodelfit.builtins.SpecifiedKnotSplineModel.rst
docs/builtins/pymodelfit.builtins.TwoPowerModel.rst
docs/builtins/pymodelfit.builtins.TwoSlopeATanModel.rst
docs/builtins/pymodelfit.builtins.TwoSlopeDiscontinuousModel.rst
docs/builtins/pymodelfit.builtins.TwoSlopeModel.rst
