Metadata-Version: 1.1
Name: PyModelFit
Version: 0.1.2
Summary: Data-fitting and Model-building package
Home-page: http:http://packages.python.org/PyModelFit/
Author: Erik Tollerud
Author-email: erik.tollerud@gmail.com
License: Apache License 2.0
Platform: UNKNOWN
Requires: numpy
Requires: scipy
Provides: pymodelfit
